imgmarker/__init__.py
imgmarker/__main__.py
imgmarker/config.py
imgmarker/heart_clear.ico
imgmarker/heart_solid.ico
imgmarker/icon.ico
imgmarker/io.py
imgmarker/tests.py
imgmarker/coordinates/__init__.py
imgmarker/gui/__init__.py
imgmarker/gui/mark.py
imgmarker/gui/pyqt.py
imgmarker/gui/widget.py
imgmarker/gui/window.py
imgmarker/image/__init__.py
imgmarker/image/convolution.py
imgmarker/image/fits.py
imgmarker-1.1.4.dist-info/licenses/LICENSE
imgmarker-1.1.4.dist-info/METADATA
imgmarker-1.1.4.dist-info/WHEEL
imgmarker-1.1.4.dist-info/entry_points.txt
imgmarker-1.1.4.dist-info/top_level.txt
imgmarker-1.1.4.dist-info/RECORD
