Metadata-Version: 2.4
Name: imgmarker
Version: 1.1.4
Summary: A package for marking objects in a series of images
Author-email: Andi Kisare <akisare@outlook.com>, Ryan Walker <astrorya@umich.edu>
License: Copyright © 2025, UChicago Argonne, LLC
Project-URL: Homepage, https://github.com/andikisare/imgmarker
Project-URL: Issues, https://github.com/andikisare/imgmarker/issues
License-File: LICENSE
Requires-Dist: astropy>=5.2.2
Requires-Dist: pillow>=10.4.0
Requires-Dist: PyQt6>=6.7.1
Requires-Dist: scipy>=1.10.1
Dynamic: license-file
